LICENSE
MANIFEST.in
README.md
setup.cfg
setup.py
lifoid_dialogflow/__init__.py
lifoid_dialogflow/config.py
lifoid_dialogflow/parser.py
lifoid_dialogflow.egg-info/PKG-INFO
lifoid_dialogflow.egg-info/SOURCES.txt
lifoid_dialogflow.egg-info/dependency_links.txt
lifoid_dialogflow.egg-info/requires.txt
lifoid_dialogflow.egg-info/top_level.txt
tests/__init__.py
tests/tests.py