Metadata-Version: 1.1
Name: lifoid-dialogflow
Version: 0.1.0
Summary: Dialogflow plugin for Lifoid
Home-page: https://github.com/romaryd/lifoid-dialogflow
Author: Romary Dupuis
Author-email: romary@me.com
License:                                  Apache License
